pyresponse/__init__.py
pyresponse/response.py
tests/__init__.py
tests/test_responses.py
pyresponse_paradox-0.2.1.dist-info/LICENSE
pyresponse_paradox-0.2.1.dist-info/METADATA
pyresponse_paradox-0.2.1.dist-info/WHEEL
pyresponse_paradox-0.2.1.dist-info/top_level.txt
pyresponse_paradox-0.2.1.dist-info/RECORD
