Metadata-Version: 2.2
Name: pyresponse-paradox
Version: 0.2.1
Summary: A simple Python package for standardized API responses.
Home-page: https://github.com/Edwardndiyo/PyResponse
Author: Edward Ndiyo
Author-email: NdiyoEdward@gmail.com
License: MIT
Classifier: Programming Language :: Python :: 3
Classifier: License :: OSI Approved :: MIT License
Classifier: Operating System :: OS Independent
Requires-Python: >=3.6
License-File: LICENSE
Requires-Dist: fastapi
Requires-Dist: flask
Requires-Dist: pydantic
Requires-Dist: typing-extensions
Dynamic: author
Dynamic: author-email
Dynamic: classifier
Dynamic: description
Dynamic: description-content-type
Dynamic: home-page
Dynamic: license
Dynamic: requires-dist
Dynamic: requires-python
Dynamic: summary
